hyperbee/__init__.py
hyperbee/_client.py
hyperbee/_version.py
hyperbee/version.py
hyperbee/resources/__init__.py
hyperbee/resources/completions.py
hyperbee/resources/models.py
hyperbee/resources/batch_request/__init__.py
hyperbee/resources/batch_request/batch_request.py
hyperbee/resources/chat/__init__.py
hyperbee/resources/chat/chat.py
hyperbee/resources/chat/completions.py
hyperbee/resources/pipeline/__init__.py
hyperbee/resources/pipeline/pipeline.py
hyperbee-0.0.2.9.dist-info/METADATA
hyperbee-0.0.2.9.dist-info/WHEEL
hyperbee-0.0.2.9.dist-info/RECORD
